{"paging": {"total_results": "20", "skipped": "0", "previous": null, "results": "20", "next": null}, "data": [{"lang": "en", "rating": 5, "travel_date": "2016-09", "title": "ribs", "url": "https://www.tripadvisor.com/ShowUserReviews-g32273-d350037-r419620414-m11068-Armadillo_Willy_s-Cupertino_California.html#review419620414", "text": "I like the ribs here, its just ribs fries and beans, but I like it, no frills sawdust on the floor maybe I should wear a cowboy hat next time I come back", "helpful_votes": "1", "rating_image_url": "http://www.tripadvisor.com/img/cdsi/img2/ratings/traveler/s5.0-11068-5.png", "subratings": [], "owner_response": null, "trip_type": "Family", "published_date": "2016-09-17T16:41:32-0400", "location_id": "350037", "id": "419620414", "user": {"username": "rudithedog2016", "user_location": {"name": "Limerick, Ireland", "id": "186621"}}}, {"lang": "en", "rating": 4, "travel_date": "2016-09", "title": "not Texas, but as close as you can get in California", "url": "https://www.tripadvisor.com/ShowUserReviews-g32273-d350037-r417707488-m11068-Armadillo_Willy_s-Cupertino_California.html#review417707488", "text": "We have been eating at the Cupertino restaurant for over 20 years and feel it is as close to genuine Texas Bar-B-Q as you can get in California.  The food is always smoked and slow cooked and the quality is consistent.  Mid range on price, but great value for the food.", "helpful_votes": "1", "rating_image_url": "http://www.tripadvisor.com/img/cdsi/img2/ratings/traveler/s4.0-11068-5.png", "subratings": [{"localized_name": "Service", "name": "rate_service", "value": "4", "rating_image_url": "https://static.tacdn.com/img2/ratings/traveler/ss4.0.gif"}, {"localized_name": "Value", "name": "rate_value", "value": "4", "rating_image_url": "https://static.tacdn.com/img2/ratings/traveler/ss4.0.gif"}, {"localized_name": "Food", "name": "rate_food", "value": "5", "rating_image_url": "https://static.tacdn.com/img2/ratings/traveler/ss5.0.gif"}], "owner_response": null, "trip_type": "Couples", "published_date": "2016-09-12T17:32:48-0400", "location_id": "350037", "id": "417707488", "user": {"username": "Jimmy M", "user_location": {"name": "Cupertino, California", "id": "32273"}}}, {"lang": "en", "rating": 5, "travel_date": "2016-05", "title": "Great Ribs", "url": "https://www.tripadvisor.com/ShowUserReviews-g32273-d350037-r413846927-m11068-Armadillo_Willy_s-Cupertino_California.html#review413846927", "text": "Armadillo Willy's is located in several places in SC County.  The ribs are very good.  They started in Los Altos, over 30 years ago and I've eaten at a couple of there locations.  The food and service is always very good.", "helpful_votes": "1", "rating_image_url": "http://www.tripadvisor.com/img/cdsi/img2/ratings/traveler/s5.0-11068-5.png", "subratings": [{"localized_name": "Service", "name": "rate_service", "value": "5", "rating_image_url": "https://static.tacdn.com/img2/ratings/traveler/ss5.0.gif"}, {"localized_name": "Value", "name": "rate_value", "value": "5", "rating_image_url": "https://static.tacdn.com/img2/ratings/traveler/ss5.0.gif"}, {"localized_name": "Food", "name": "rate_food", "value": "5", "rating_image_url": "https://static.tacdn.com/img2/ratings/traveler/ss5.0.gif"}], "owner_response": null, "trip_type": "Couples", "published_date": "2016-09-02T05:06:30-0400", "location_id": "350037", "id": "413846927", "user": {"username": "Jon R", "user_location": {"name": null, "id": null}}}, {"lang": "en", "rating": 2, "travel_date": "2016-08", "title": "Texans won't recognize this as BBQ - but...", "url": "https://www.tripadvisor.com/ShowUserReviews-g32273-d350037-r413533836-m11068-Armadillo_Willy_s-Cupertino_California.html#review413533836", "text": "... it's not so bad as a brisket or chicken smoked flavor.  Sauce is a bit thin and overall the kitchen-grease smells could use a top-down steam cleaning.", "helpful_votes": "1", "rating_image_url": "http://www.tripadvisor.com/img/cdsi/img2/ratings/traveler/s2.0-11068-5.png", "subratings": [], "owner_response": null, "trip_type": "Business", "published_date": "2016-09-01T07:10:48-0400", "location_id": "350037", "id": "413533836", "user": {"username": "Gwhized", "user_location": {"name": "Austin, Texas", "id": "30196"}}}, {"lang": "en", "rating": 5, "travel_date": "2016-08", "title": "Yummy", "url": "https://www.tripadvisor.com/ShowUserReviews-g32273-d350037-r403826973-m11068-Armadillo_Willy_s-Cupertino_California.html#review403826973", "text": "The selection is great. The tri-tip is perfect every time. It is realitively quick and a great place to meet up with friends or take the kids. Very casual and comfortable. ", "helpful_votes": "1", "rating_image_url": "http://www.tripadvisor.com/img/cdsi/img2/ratings/traveler/s5.0-11068-5.png", "subratings": [], "owner_response": null, "trip_type": "Family", "published_date": "2016-08-10T14:27:32-0400", "location_id": "350037", "id": "403826973", "user": {"username": "travel4fun111", "user_location": {"name": "silicon valley", "id": null}}}, {"lang": "en", "rating": 5, "travel_date": "2016-07", "title": "Good food and value", "url": "https://www.tripadvisor.com/ShowUserReviews-g32273-d350037-r397050887-m11068-Armadillo_Willy_s-Cupertino_California.html#review397050887", "text": "My friend had the ribs and brisket special with macaroni and cheese.  She said it was great.  The meat was very tender.  I had the blackened salmon burger with a small salad.  It was delicious.", "helpful_votes": "1", "rating_image_url": "http://www.tripadvisor.com/img/cdsi/img2/ratings/traveler/s5.0-11068-5.png", "subratings": [], "owner_response": null, "trip_type": "Family", "published_date": "2016-07-25T17:47:35-0400", "location_id": "350037", "id": "397050887", "user": {"username": "Sybil N", "user_location": {"name": null, "id": null}}}, {"lang": "en", "rating": 4, "travel_date": "2016-06", "title": "Great BBQ", "url": "https://www.tripadvisor.com/ShowUserReviews-g32273-d350037-r394471111-m11068-Armadillo_Willy_s-Cupertino_California.html#review394471111", "text": "This is a place that you want to enjoy real BBQ dish, very good flavor and good potion for the price, I especially like ribs, they are cook perfectly, the best thing is no tone of sauce on top of it, very satisfying place for dinner.", "helpful_votes": "1", "rating_image_url": "http://www.tripadvisor.com/img/cdsi/img2/ratings/traveler/s4.0-11068-5.png", "subratings": [{"localized_name": "Service", "name": "rate_service", "value": "4", "rating_image_url": "https://static.tacdn.com/img2/ratings/traveler/ss4.0.gif"}, {"localized_name": "Value", "name": "rate_value", "value": "4", "rating_image_url": "https://static.tacdn.com/img2/ratings/traveler/ss4.0.gif"}, {"localized_name": "Food", "name": "rate_food", "value": "4", "rating_image_url": "https://static.tacdn.com/img2/ratings/traveler/ss4.0.gif"}], "owner_response": null, "trip_type": "Couples", "published_date": "2016-07-19T14:46:57-0400", "location_id": "350037", "id": "394471111", "user": {"username": "220fran", "user_location": {"name": "Cupertino, California", "id": "32273"}}}, {"lang": "en", "rating": 5, "travel_date": "2016-07", "title": "Great Texan food", "url": "https://www.tripadvisor.com/ShowUserReviews-g32273-d350037-r392514748-m11068-Armadillo_Willy_s-Cupertino_California.html#review392514748", "text": "Fab food, especially the brisket, large portions, I shared a meal with my wife and was still full. Reasonable price, mains about 17 dollars \n", "helpful_votes": "1", "rating_image_url": "http://www.tripadvisor.com/img/cdsi/img2/ratings/traveler/s5.0-11068-5.png", "subratings": [], "owner_response": null, "trip_type": null, "published_date": "2016-07-14T06:30:53-0400", "location_id": "350037", "id": "392514748", "user": {"username": "patrick028", "user_location": {"name": "Worcester, United Kingdom", "id": "186424"}}}, {"lang": "en", "rating": 5, "travel_date": "2016-06", "title": "Ate it all, oh my!", "url": "https://www.tripadvisor.com/ShowUserReviews-g32273-d350037-r386206839-m11068-Armadillo_Willy_s-Cupertino_California.html#review386206839", "text": "Went with coworkers and loved it. They give you a lot of food and my 110 pound self ate it all. Got the pulled pork with potato salad and the corn muffin. \n\nMy coworkers got the baby back ribs, brisket (juicy) and a variety platter. Everyone stuffed themselves. \n\nIt's very casual which was nice after a long day of hard work and travel. \n\nStaff was friendly. ", "helpful_votes": "1", "rating_image_url": "http://www.tripadvisor.com/img/cdsi/img2/ratings/traveler/s5.0-11068-5.png", "subratings": [], "owner_response": null, "trip_type": "Business", "published_date": "2016-06-26T13:03:28-0400", "location_id": "350037", "id": "386206839", "user": {"username": "Toby M", "user_location": {"name": null, "id": null}}}, {"lang": "en", "rating": 5, "travel_date": "2016-06", "title": "Best BBQ in the area by far", "url": "https://www.tripadvisor.com/ShowUserReviews-g32273-d350037-r384667309-m11068-Armadillo_Willy_s-Cupertino_California.html#review384667309", "text": "BBQ meat cooked to perfection. Every dish is a hit. No misses. Superb brisket. Succulent pulled pork. Excellent ribs. Great sides - I especially like the peanut-slaw and corn salad (cilantro alert). Puffy cornbread muffins, served warm and fresh. I could eat here every day.", "helpful_votes": "1", "rating_image_url": "http://www.tripadvisor.com/img/cdsi/img2/ratings/traveler/s5.0-11068-5.png", "subratings": [{"localized_name": "Service", "name": "rate_service", "value": "5", "rating_image_url": "https://static.tacdn.com/img2/ratings/traveler/ss5.0.gif"}, {"localized_name": "Value", "name": "rate_value", "value": "5", "rating_image_url": "https://static.tacdn.com/img2/ratings/traveler/ss5.0.gif"}, {"localized_name": "Food", "name": "rate_food", "value": "5", "rating_image_url": "https://static.tacdn.com/img2/ratings/traveler/ss5.0.gif"}], "owner_response": null, "trip_type": "Family", "published_date": "2016-06-21T11:08:30-0400", "location_id": "350037", "id": "384667309", "user": {"username": "Ran H", "user_location": {"name": "Los Altos, United States", "id": null}}}, {"lang": "en", "rating": 4, "travel_date": "2016-06", "title": "Great staff and better food for BBQ", "url": "https://www.tripadvisor.com/ShowUserReviews-g32273-d350037-r380991478-m11068-Armadillo_Willy_s-Cupertino_California.html#review380991478", "text": "Only reason I didn't give them 5 stars was the Side BBQ Beans were not sweet, BBQ or have any flavor but celery!.\n\nThis is a MUST HIT for BBQ when in the area.  Staff are great, I was able to try the Firestone Draft Beer and it was winner.\n\nI had the Trinity BBQ Plate with Excellent & Taste Sausage has a bit of a nice kick.\nThe Ribs and brisket were also good.", "helpful_votes": "1", "rating_image_url": "http://www.tripadvisor.com/img/cdsi/img2/ratings/traveler/s4.0-11068-5.png", "subratings": [{"localized_name": "Service", "name": "rate_service", "value": "5", "rating_image_url": "https://static.tacdn.com/img2/ratings/traveler/ss5.0.gif"}, {"localized_name": "Value", "name": "rate_value", "value": "5", "rating_image_url": "https://static.tacdn.com/img2/ratings/traveler/ss5.0.gif"}, {"localized_name": "Food", "name": "rate_food", "value": "4", "rating_image_url": "https://static.tacdn.com/img2/ratings/traveler/ss4.0.gif"}], "owner_response": null, "trip_type": "Solo travel", "published_date": "2016-06-08T18:09:01-0400", "location_id": "350037", "id": "380991478", "user": {"username": "scubasam", "user_location": {"name": "Upstate NY", "id": null}}}, {"lang": "en", "rating": 4, "travel_date": "2016-04", "title": "Good food and nice staff", "url": "https://www.tripadvisor.com/ShowUserReviews-g32273-d350037-r377564969-m11068-Armadillo_Willy_s-Cupertino_California.html#review377564969", "text": "I went there for a quick dinner and something to drink.\nPleased by the nice staff and the help to chose the food (I am not a Tex folk :-) ), good beer.\nIt is a simple restaurant, but if you look for tasty and juicy food this is the place to go.", "helpful_votes": "1", "rating_image_url": "http://www.tripadvisor.com/img/cdsi/img2/ratings/traveler/s4.0-11068-5.png", "subratings": [{"localized_name": "Service", "name": "rate_service", "value": "4", "rating_image_url": "https://static.tacdn.com/img2/ratings/traveler/ss4.0.gif"}, {"localized_name": "Value", "name": "rate_value", "value": "3", "rating_image_url": "https://static.tacdn.com/img2/ratings/traveler/ss3.0.gif"}, {"localized_name": "Food", "name": "rate_food", "value": "4", "rating_image_url": "https://static.tacdn.com/img2/ratings/traveler/ss4.0.gif"}], "owner_response": null, "trip_type": "Solo travel", "published_date": "2016-05-29T04:41:15-0400", "location_id": "350037", "id": "377564969", "user": {"username": "Ricc57", "user_location": {"name": "Verderio, Italy", "id": "3490701"}}}, {"lang": "en", "rating": 4, "travel_date": "2016-05", "title": "Brisket", "url": "https://www.tripadvisor.com/ShowUserReviews-g32273-d350037-r376277091-m11068-Armadillo_Willy_s-Cupertino_California.html#review376277091", "text": "Go for the brisket (juicy). Tritip is good too.  Have a couple of beers on tap and let me sample the ones that were of interest.", "helpful_votes": "1", "rating_image_url": "http://www.tripadvisor.com/img/cdsi/img2/ratings/traveler/s4.0-11068-5.png", "subratings": [], "owner_response": null, "trip_type": "Business", "published_date": "2016-05-24T17:36:00-0400", "location_id": "350037", "id": "376277091", "user": {"username": "LiangShanBo", "user_location": {"name": "Shanghai", "id": null}}}, {"lang": "en", "rating": 5, "travel_date": "2016-04", "title": "Armadillo Willy's is an old favorite", "url": "https://www.tripadvisor.com/ShowUserReviews-g32273-d350037-r368858647-m11068-Armadillo_Willy_s-Cupertino_California.html#review368858647", "text": "Armadillo Willy's was literally born in Cupertino.  Their original place was across the street from the current location.  They are headquartered now in Los Altos.\n\nThe place has been consistently good..   I have even had them cater over the years  for a events of public service organizations.   If you like beef, you will like their BBQ.  They even serve prime brisket.   You now get a choice of Prime with the fat , original lean brisket , or a mix.\nAs I have aged into senior status, I find my appetite now as large.  My wife and I order a small plate with a smaller portion and only one side.  It works great for us.\n\nThey have adapted over the years, but they still slow roast their briskets.  Their Tri-Tip is also excellent.  Very informal, great service, and everyone in this  area knows of them.  Great value in this area.  They own the building so they can keep their prices reasonable.", "helpful_votes": "1", "rating_image_url": "http://www.tripadvisor.com/img/cdsi/img2/ratings/traveler/s5.0-11068-5.png", "subratings": [{"localized_name": "Service", "name": "rate_service", "value": "5", "rating_image_url": "https://static.tacdn.com/img2/ratings/traveler/ss5.0.gif"}, {"localized_name": "Value", "name": "rate_value", "value": "5", "rating_image_url": "https://static.tacdn.com/img2/ratings/traveler/ss5.0.gif"}, {"localized_name": "Food", "name": "rate_food", "value": "5", "rating_image_url": "https://static.tacdn.com/img2/ratings/traveler/ss5.0.gif"}], "owner_response": null, "trip_type": "Friends getaway", "published_date": "2016-04-29T19:36:50-0400", "location_id": "350037", "id": "368858647", "user": {"username": "Eaglepipeclub", "user_location": {"name": "Cupertino, California", "id": "32273"}}}, {"lang": "en", "rating": 4, "travel_date": "2016-02", "title": "GOOD FOOD", "url": "https://www.tripadvisor.com/ShowUserReviews-g32273-d350037-r366178912-m11068-Armadillo_Willy_s-Cupertino_California.html#review366178912", "text": "Excellent BBQ.  Rich full flavored.  Fast efficient service.  Tastes Great, and is filling.  Worth going out forl.", "helpful_votes": "1", "rating_image_url": "http://www.tripadvisor.com/img/cdsi/img2/ratings/traveler/s4.0-11068-5.png", "subratings": [{"localized_name": "Service", "name": "rate_service", "value": "5", "rating_image_url": "https://static.tacdn.com/img2/ratings/traveler/ss5.0.gif"}, {"localized_name": "Value", "name": "rate_value", "value": "4", "rating_image_url": "https://static.tacdn.com/img2/ratings/traveler/ss4.0.gif"}, {"localized_name": "Food", "name": "rate_food", "value": "4", "rating_image_url": "https://static.tacdn.com/img2/ratings/traveler/ss4.0.gif"}], "owner_response": null, "trip_type": "Family", "published_date": "2016-04-21T14:28:08-0400", "location_id": "350037", "id": "366178912", "user": {"username": "Vivian A", "user_location": {"name": "Sunnyvale, California, United States", "id": null}}}, {"lang": "en", "rating": 5, "travel_date": "2016-03", "title": "Best BBQ outside of Texas", "url": "https://www.tripadvisor.com/ShowUserReviews-g32273-d350037-r357982506-m11068-Armadillo_Willy_s-Cupertino_California.html#review357982506", "text": "Always a tasty experience there.  Great brisket and ribs for lunch or dinner.  Good decor and friendly counter people.", "helpful_votes": "1", "rating_image_url": "http://www.tripadvisor.com/img/cdsi/img2/ratings/traveler/s5.0-11068-5.png", "subratings": [], "owner_response": null, "trip_type": "Family", "published_date": "2016-03-23T16:04:05-0400", "location_id": "350037", "id": "357982506", "user": {"username": "Jerry T", "user_location": {"name": null, "id": null}}}, {"lang": "en", "rating": 4, "travel_date": "2016-03", "title": "Great food and wonderful employees!!", "url": "https://www.tripadvisor.com/ShowUserReviews-g32273-d350037-r357711417-m11068-Armadillo_Willy_s-Cupertino_California.html#review357711417", "text": "I was recently traveling in Cupertino and met my friends at Armadillo Willy's for lunch! The food was wonderful and the staff were really friendly and fun. We told them about deep fried pickles and while we ate our lunch, they were back in the kitchen, trying to make them! Such fun!!!", "helpful_votes": "1", "rating_image_url": "http://www.tripadvisor.com/img/cdsi/img2/ratings/traveler/s4.0-11068-5.png", "subratings": [], "owner_response": null, "trip_type": "Solo travel", "published_date": "2016-03-22T19:14:44-0400", "location_id": "350037", "id": "357711417", "user": {"username": "Elizabeth F", "user_location": {"name": "Damascus, Maryland", "id": "41099"}}}, {"lang": "en", "rating": 3, "travel_date": "2016-01", "title": "Smoked meats are wonderful. Service can be spotty.", "url": "https://www.tripadvisor.com/ShowUserReviews-g32273-d350037-r349557429-m11068-Armadillo_Willy_s-Cupertino_California.html#review349557429", "text": "Basics are smoked meats and for this they are wonderful.  Service can be spotty at ordering or at pick-up.  Most times everything is wonderful, but a rough edge can pop up without warning.", "helpful_votes": "1", "rating_image_url": "http://www.tripadvisor.com/img/cdsi/img2/ratings/traveler/s3.0-11068-5.png", "subratings": [{"localized_name": "Service", "name": "rate_service", "value": "3", "rating_image_url": "https://static.tacdn.com/img2/ratings/traveler/ss3.0.gif"}, {"localized_name": "Value", "name": "rate_value", "value": "4", "rating_image_url": "https://static.tacdn.com/img2/ratings/traveler/ss4.0.gif"}, {"localized_name": "Food", "name": "rate_food", "value": "4", "rating_image_url": "https://static.tacdn.com/img2/ratings/traveler/ss4.0.gif"}], "owner_response": null, "trip_type": "Family", "published_date": "2016-02-20T20:27:50-0500", "location_id": "350037", "id": "349557429", "user": {"username": "Snoopydad1", "user_location": {"name": "Cupertino, California", "id": "32273"}}}, {"lang": "en", "rating": 4, "travel_date": "2016-02", "title": "Affordable BBQ -- fantastic peanut slaw", "url": "https://www.tripadvisor.com/ShowUserReviews-g32273-d350037-r346016000-m11068-Armadillo_Willy_s-Cupertino_California.html#review346016000", "text": "Their version of cole slaw has peanuts and it is one of the best things about Armadillo Willy's.  They let you put your own choice of sauce on the meats which are generally juicy and tender.  The corn bread muffins are good also.", "helpful_votes": "1", "rating_image_url": "http://www.tripadvisor.com/img/cdsi/img2/ratings/traveler/s4.0-11068-5.png", "subratings": [{"localized_name": "Service", "name": "rate_service", "value": "4", "rating_image_url": "https://static.tacdn.com/img2/ratings/traveler/ss4.0.gif"}, {"localized_name": "Value", "name": "rate_value", "value": "4", "rating_image_url": "https://static.tacdn.com/img2/ratings/traveler/ss4.0.gif"}, {"localized_name": "Food", "name": "rate_food", "value": "4", "rating_image_url": "https://static.tacdn.com/img2/ratings/traveler/ss4.0.gif"}], "owner_response": null, "trip_type": "Family", "published_date": "2016-02-08T19:06:12-0500", "location_id": "350037", "id": "346016000", "user": {"username": "eric95014", "user_location": {"name": "Silicon Valley", "id": null}}}, {"lang": "en", "rating": 4, "travel_date": "2015-05", "title": "Good BBQ", "url": "https://www.tripadvisor.com/ShowUserReviews-g32273-d350037-r345936336-m11068-Armadillo_Willy_s-Cupertino_California.html#review345936336", "text": "Love Willy's.  The Cupertino and Sunnyvale location are very good. They are quick and the food is good. Sometimes the ribs can be a tad on the cool side, but they fix that right away. I've never had to wait longer than 5 minutes to get to the register to order and not very long to get food, even during lunch time.", "helpful_votes": "1", "rating_image_url": "http://www.tripadvisor.com/img/cdsi/img2/ratings/traveler/s4.0-11068-5.png", "subratings": [{"localized_name": "Service", "name": "rate_service", "value": "5", "rating_image_url": "https://static.tacdn.com/img2/ratings/traveler/ss5.0.gif"}, {"localized_name": "Value", "name": "rate_value", "value": "5", "rating_image_url": "https://static.tacdn.com/img2/ratings/traveler/ss5.0.gif"}, {"localized_name": "Food", "name": "rate_food", "value": "5", "rating_image_url": "https://static.tacdn.com/img2/ratings/traveler/ss5.0.gif"}], "owner_response": null, "trip_type": "Friends getaway", "published_date": "2016-02-08T12:24:34-0500", "location_id": "350037", "id": "345936336", "user": {"username": "Peter E", "user_location": {"name": null, "id": null}}}]}