{"paging": {"total_results": "10", "skipped": "0", "previous": null, "results": "10", "next": null}, "data": [{"rating": "3.5", "subcategory": [{"localized_name": "Sit down", "name": "sit_down"}], "bearing": "south", "rating_image_url": "http://www.tripadvisor.com/img/cdsi/img2/ratings/traveler/3.5-11068-5.png", "web_url": "https://www.tripadvisor.com/Restaurant_Review-g55870-d460668-Reviews-m11068-Randy_s_Steakhouse-Frisco_Texas.html", "location_id": "460668", "write_review": "https://www.tripadvisor.com/UserReview-g55870-d460668-m11068-Randy_s_Steakhouse-Frisco_Texas.html", "cuisine": [{"localized_name": "American", "name": "american"}, {"localized_name": "Steakhouse", "name": "steakhouse"}], "ancestors": [{"abbrv": null, "location_id": "55870", "name": "Frisco", "level": "City"}, {"abbrv": "TX", "location_id": "28964", "name": "Texas", "level": "State"}, {"abbrv": null, "location_id": "191", "name": "United States", "level": "Country"}], "location_string": "Frisco, Texas", "price_level": "$$$$", "latitude": "33.150417", "category": {"localized_name": "Restaurant", "name": "restaurant"}, "ranking_data": {"ranking_string": "#98 of 398 Places to Eat in Frisco", "ranking": "98", "geo_location_name": "Frisco", "geo_location_id": "55870", "ranking_out_of": "398"}, "api_detail_url": "http://api.tripadvisor.com/api/partner/2.0/location/460668?key=b245d5db-8cc1-4cb9-a499-90602105b49b", "num_reviews": "124", "awards": [], "percent_recommended": 54, "distance": ".02", "name": "Randy's Steakhouse", "see_all_photos": "https://www.tripadvisor.com/Restaurant_Review-g55870-d460668-m11068-Reviews-Randy_s_Steakhouse-Frisco_Texas.html#photos", "hours": {"timezone": "America/Chicago", "week_ranges": [{"day_name": "Sunday", "localized_day_name": "Sunday", "times": [{"close_time": "22:00", "open_time": "17:00"}]}, {"day_name": "Monday", "localized_day_name": "Monday", "times": [{"close_time": "22:00", "open_time": "17:00"}]}, {"day_name": "Tuesday", "localized_day_name": "Tuesday", "times": [{"close_time": "22:00", "open_time": "17:00"}]}, {"day_name": "Wednesday", "localized_day_name": "Wednesday", "times": [{"close_time": "22:00", "open_time": "17:00"}]}, {"day_name": "Thursday", "localized_day_name": "Thursday", "times": [{"close_time": "22:00", "open_time": "17:00"}]}, {"day_name": "Friday", "localized_day_name": "Friday", "times": [{"close_time": "22:00", "open_time": "17:00"}]}, {"day_name": "Saturday", "localized_day_name": "Saturday", "times": [{"close_time": "22:00", "open_time": "17:00"}]}]}, "address_obj": {"city": "Frisco", "street1": "7026 Main Street", "street2": "", "address_string": "7026 Main Street, Frisco, TX 75033", "state": "Texas", "country": "United States", "postalcode": "75033"}, "longitude": "-96.82349"}, {"rating": "4.5", "subcategory": [], "bearing": "southeast", "rating_image_url": "http://www.tripadvisor.com/img/cdsi/img2/ratings/traveler/4.5-11068-5.png", "web_url": "https://www.tripadvisor.com/Restaurant_Review-g55870-d5456035-Reviews-m11068-Eight11-Frisco_Texas.html", "location_id": "5456035", "write_review": "https://www.tripadvisor.com/UserReview-g55870-d5456035-m11068-Eight11-Frisco_Texas.html", "cuisine": [{"localized_name": "Wine Bar", "name": "wine_bar"}], "ancestors": [{"abbrv": null, "location_id": "55870", "name": "Frisco", "level": "City"}, {"abbrv": "TX", "location_id": "28964", "name": "Texas", "level": "State"}, {"abbrv": null, "location_id": "191", "name": "United States", "level": "Country"}], "location_string": "Frisco, Texas", "price_level": "$$ - $$$", "latitude": "33.15034", "category": {"localized_name": "Restaurant", "name": "restaurant"}, "ranking_data": {"ranking_string": "#79 of 398 Places to Eat in Frisco", "ranking": "79", "geo_location_name": "Frisco", "geo_location_id": "55870", "ranking_out_of": "398"}, "api_detail_url": "http://api.tripadvisor.com/api/partner/2.0/location/5456035?key=b245d5db-8cc1-4cb9-a499-90602105b49b", "num_reviews": "14", "awards": [], "percent_recommended": null, "distance": ".05", "name": "eight11", "see_all_photos": "https://www.tripadvisor.com/Restaurant_Review-g55870-d5456035-m11068-Reviews-Eight11-Frisco_Texas.html#photos", "hours": {"timezone": "America/Chicago", "week_ranges": [{"day_name": "Sunday", "localized_day_name": "Sunday", "times": []}, {"day_name": "Monday", "localized_day_name": "Monday", "times": [{"close_time": "22:00", "open_time": "16:00"}]}, {"day_name": "Tuesday", "localized_day_name": "Tuesday", "times": [{"close_time": "22:00", "open_time": "16:00"}]}, {"day_name": "Wednesday", "localized_day_name": "Wednesday", "times": [{"close_time": "22:00", "open_time": "16:00"}]}, {"day_name": "Thursday", "localized_day_name": "Thursday", "times": [{"close_time": "22:00", "open_time": "16:00"}]}, {"day_name": "Friday", "localized_day_name": "Friday", "times": [{"close_time": "22:00", "open_time": "16:00"}]}, {"day_name": "Saturday", "localized_day_name": "Saturday", "times": [{"close_time": "22:00", "open_time": "16:00"}]}]}, "address_obj": {"city": "Frisco", "street1": "7080 W. Main Street", "street2": null, "address_string": "7080 W. Main Street, Frisco, TX 75034", "state": "Texas", "country": "United States", "postalcode": "75034"}, "longitude": "-96.8229"}, {"rating": "4.5", "subcategory": [{"localized_name": "Sit down", "name": "sit_down"}], "bearing": "west", "rating_image_url": "http://www.tripadvisor.com/img/cdsi/img2/ratings/traveler/4.5-11068-5.png", "web_url": "https://www.tripadvisor.com/Restaurant_Review-g55870-d3255084-Reviews-m11068-Mariana_s_Taco_Shop-Frisco_Texas.html", "location_id": "3255084", "write_review": "https://www.tripadvisor.com/UserReview-g55870-d3255084-m11068-Mariana_s_Taco_Shop-Frisco_Texas.html", "cuisine": [{"localized_name": "Mexican", "name": "mexican"}, {"localized_name": "Latin", "name": "latin"}, {"localized_name": "Spanish", "name": "spanish"}], "ancestors": [{"abbrv": null, "location_id": "55870", "name": "Frisco", "level": "City"}, {"abbrv": "TX", "location_id": "28964", "name": "Texas", "level": "State"}, {"abbrv": null, "location_id": "191", "name": "United States", "level": "Country"}], "location_string": "Frisco, Texas", "price_level": "$", "latitude": "33.15102", "category": {"localized_name": "Restaurant", "name": "restaurant"}, "ranking_data": {"ranking_string": "#102 of 398 Places to Eat in Frisco", "ranking": "102", "geo_location_name": "Frisco", "geo_location_id": "55870", "ranking_out_of": "398"}, "api_detail_url": "http://api.tripadvisor.com/api/partner/2.0/location/3255084?key=b245d5db-8cc1-4cb9-a499-90602105b49b", "num_reviews": "13", "awards": [], "percent_recommended": null, "distance": ".09", "name": "Mariana's Taco Shop", "see_all_photos": "https://www.tripadvisor.com/Restaurant_Review-g55870-d3255084-m11068-Reviews-Mariana_s_Taco_Shop-Frisco_Texas.html#photos", "hours": {"timezone": "America/Chicago", "week_ranges": [{"day_name": "Sunday", "localized_day_name": "Sunday", "times": [{"close_time": "15:00", "open_time": "09:00"}]}, {"day_name": "Monday", "localized_day_name": "Monday", "times": [{"close_time": "20:00", "open_time": "08:00"}]}, {"day_name": "Tuesday", "localized_day_name": "Tuesday", "times": [{"close_time": "20:00", "open_time": "08:00"}]}, {"day_name": "Wednesday", "localized_day_name": "Wednesday", "times": [{"close_time": "20:00", "open_time": "08:00"}]}, {"day_name": "Thursday", "localized_day_name": "Thursday", "times": [{"close_time": "20:00", "open_time": "08:00"}]}, {"day_name": "Friday", "localized_day_name": "Friday", "times": [{"close_time": "21:00", "open_time": "08:00"}]}, {"day_name": "Saturday", "localized_day_name": "Saturday", "times": [{"close_time": "21:00", "open_time": "08:00"}]}]}, "address_obj": {"city": "Frisco", "street1": "6890 Main St", "street2": "Suite D", "address_string": "6890 Main St Suite D, Frisco, TX 75033-4250", "state": "Texas", "country": "United States", "postalcode": "75033-4250"}, "longitude": "-96.82517"}, {"rating": "4.5", "subcategory": [{"localized_name": "Sights & Landmarks", "name": "landmarks"}, {"localized_name": "Attractions", "name": "attractions"}], "bearing": "southeast", "rating_image_url": "http://www.tripadvisor.com/img/cdsi/img2/ratings/traveler/4.5-11068-5.png", "web_url": "https://www.tripadvisor.com/Attraction_Review-g55870-d616435-Reviews-m11068-Frisco_Soccer_Complex-Frisco_Texas.html", "location_id": "616435", "write_review": "https://www.tripadvisor.com/UserReview-g55870-d616435-m11068-Frisco_Soccer_Complex-Frisco_Texas.html", "ancestors": [{"abbrv": null, "location_id": "55870", "name": "Frisco", "level": "City"}, {"abbrv": "TX", "location_id": "28964", "name": "Texas", "level": "State"}, {"abbrv": null, "location_id": "191", "name": "United States", "level": "Country"}], "location_string": "Frisco, Texas", "ranking_data": {"ranking_string": "#10 of 29 things to do in Frisco", "ranking": "10", "geo_location_name": "Frisco", "geo_location_id": "55870", "ranking_out_of": "29"}, "latitude": "33.15013", "category": {"localized_name": "Attraction", "name": "attraction"}, "attraction_types": [{"localized_name": "Arenas & Stadiums", "name": "arenas/ stadiums/ fields"}], "api_detail_url": "http://api.tripadvisor.com/api/partner/2.0/location/616435?key=b245d5db-8cc1-4cb9-a499-90602105b49b", "num_reviews": "35", "awards": [], "percent_recommended": 96, "wikipedia_info": null, "distance": ".10", "name": "Frisco Soccer Complex", "see_all_photos": "https://www.tripadvisor.com/Attraction_Review-g55870-d616435-m11068-Reviews-Frisco_Soccer_Complex-Frisco_Texas.html#photos", "hours": null, "address_obj": {"city": "Frisco", "street1": "Main St.", "street2": "", "address_string": "Main St., Frisco, TX", "state": "Texas", "country": "United States", "postalcode": ""}, "longitude": "-96.82207"}, {"rating": "4.5", "subcategory": [{"localized_name": "Classes & Workshops", "name": "classes"}, {"localized_name": "Activities", "name": "activities"}], "bearing": "west", "rating_image_url": "http://www.tripadvisor.com/img/cdsi/img2/ratings/traveler/4.5-11068-5.png", "web_url": "https://www.tripadvisor.com/Attraction_Review-g55870-d3976941-Reviews-m11068-Sip_n_Doodle_Paint_Party_Sudio-Frisco_Texas.html", "location_id": "3976941", "write_review": "https://www.tripadvisor.com/UserReview-g55870-d3976941-m11068-Sip_n_Doodle_Paint_Party_Sudio-Frisco_Texas.html", "ancestors": [{"abbrv": null, "location_id": "55870", "name": "Frisco", "level": "City"}, {"abbrv": "TX", "location_id": "28964", "name": "Texas", "level": "State"}, {"abbrv": null, "location_id": "191", "name": "United States", "level": "Country"}], "location_string": "Frisco, Texas", "ranking_data": {"ranking_string": "#1 of 1 Classes &amp; Workshops in Frisco", "ranking": "1", "geo_location_name": "Frisco", "geo_location_id": "55870", "ranking_out_of": "1"}, "latitude": "33.15112", "category": {"localized_name": "Attraction", "name": "attraction"}, "attraction_types": [{"localized_name": "Lessons & Workshops", "name": "classes/workshops"}], "api_detail_url": "http://api.tripadvisor.com/api/partner/2.0/location/3976941?key=b245d5db-8cc1-4cb9-a499-90602105b49b", "num_reviews": "49", "awards": [], "percent_recommended": null, "wikipedia_info": null, "distance": ".12", "name": "Sip-n-Doodle Paint Party Sudio", "see_all_photos": "https://www.tripadvisor.com/Attraction_Review-g55870-d3976941-m11068-Reviews-Sip_n_Doodle_Paint_Party_Sudio-Frisco_Texas.html#photos", "hours": null, "address_obj": {"city": "Frisco", "street1": "6842 Main St Ste 103", "street2": "", "address_string": "6842 Main St Ste 103, Frisco, TX 75033-4243", "state": "Texas", "country": "United States", "postalcode": "75033-4243"}, "longitude": "-96.82566"}, {"rating": "4.5", "subcategory": [{"localized_name": "Sit down", "name": "sit_down"}], "bearing": "west", "rating_image_url": "http://www.tripadvisor.com/img/cdsi/img2/ratings/traveler/4.5-11068-5.png", "web_url": "https://www.tripadvisor.com/Restaurant_Review-g55870-d4482153-Reviews-m11068-Simply_Thai_Bistro-Frisco_Texas.html", "location_id": "4482153", "write_review": "https://www.tripadvisor.com/UserReview-g55870-d4482153-m11068-Simply_Thai_Bistro-Frisco_Texas.html", "cuisine": [{"localized_name": "Asian", "name": "asian"}, {"localized_name": "Thai", "name": "thai"}], "ancestors": [{"abbrv": null, "location_id": "55870", "name": "Frisco", "level": "City"}, {"abbrv": "TX", "location_id": "28964", "name": "Texas", "level": "State"}, {"abbrv": null, "location_id": "191", "name": "United States", "level": "Country"}], "location_string": "Frisco, Texas", "price_level": "$$ - $$$", "latitude": "33.15112", "category": {"localized_name": "Restaurant", "name": "restaurant"}, "ranking_data": {"ranking_string": "#28 of 398 Places to Eat in Frisco", "ranking": "28", "geo_location_name": "Frisco", "geo_location_id": "55870", "ranking_out_of": "398"}, "api_detail_url": "http://api.tripadvisor.com/api/partner/2.0/location/4482153?key=b245d5db-8cc1-4cb9-a499-90602105b49b", "num_reviews": "55", "awards": [{"images": {"small": "http://www.tripadvisor.com/img/cdsi/img2/awards/CERTIFICATE_OF_EXCELLENCE_small-11068-5.jpg", "large": "http://www.tripadvisor.com/img/cdsi/img2/awards/CERTIFICATE_OF_EXCELLENCE_2016_en_US_large-11068-5.jpg"}, "display_name": "Certificate of Excellence 2016", "award_type": "Certificate of Excellence", "categories": [], "year": "2016"}], "percent_recommended": 95, "distance": ".12", "name": "Simply Thai Bistro", "see_all_photos": "https://www.tripadvisor.com/Restaurant_Review-g55870-d4482153-m11068-Reviews-Simply_Thai_Bistro-Frisco_Texas.html#photos", "hours": {"timezone": "America/Chicago", "week_ranges": [{"day_name": "Sunday", "localized_day_name": "Sunday", "times": [{"close_time": "22:00", "open_time": "11:00"}]}, {"day_name": "Monday", "localized_day_name": "Monday", "times": [{"close_time": "22:00", "open_time": "11:00"}]}, {"day_name": "Tuesday", "localized_day_name": "Tuesday", "times": [{"close_time": "22:00", "open_time": "11:00"}]}, {"day_name": "Wednesday", "localized_day_name": "Wednesday", "times": [{"close_time": "22:00", "open_time": "11:00"}]}, {"day_name": "Thursday", "localized_day_name": "Thursday", "times": [{"close_time": "22:00", "open_time": "11:00"}]}, {"day_name": "Friday", "localized_day_name": "Friday", "times": [{"close_time": "22:00", "open_time": "11:00"}]}, {"day_name": "Saturday", "localized_day_name": "Saturday", "times": [{"close_time": "22:00", "open_time": "11:00"}]}]}, "address_obj": {"city": "Frisco", "street1": "6842 Main St", "street2": "Suite 101", "address_string": "6842 Main St Suite 101, Frisco, TX 75033-4243", "state": "Texas", "country": "United States", "postalcode": "75033-4243"}, "longitude": "-96.82566"}, {"rating": "4.0", "subcategory": [{"localized_name": "Caf\u00e9", "name": "cafe"}], "bearing": "east", "rating_image_url": "http://www.tripadvisor.com/img/cdsi/img2/ratings/traveler/4.0-11068-5.png", "web_url": "https://www.tripadvisor.com/Restaurant_Review-g55870-d8523002-Reviews-m11068-Stan_s_Main_Street_Grill-Frisco_Texas.html", "location_id": "8523002", "write_review": "https://www.tripadvisor.com/UserReview-g55870-d8523002-m11068-Stan_s_Main_Street_Grill-Frisco_Texas.html", "cuisine": [{"localized_name": "American", "name": "american"}], "ancestors": [{"abbrv": null, "location_id": "55870", "name": "Frisco", "level": "City"}, {"abbrv": "TX", "location_id": "28964", "name": "Texas", "level": "State"}, {"abbrv": null, "location_id": "191", "name": "United States", "level": "Country"}], "location_string": "Frisco, Texas", "price_level": "$$ - $$$", "latitude": "33.150208", "category": {"localized_name": "Restaurant", "name": "restaurant"}, "ranking_data": {"ranking_string": "#170 of 398 Places to Eat in Frisco", "ranking": "170", "geo_location_name": "Frisco", "geo_location_id": "55870", "ranking_out_of": "398"}, "api_detail_url": "http://api.tripadvisor.com/api/partner/2.0/location/8523002?key=b245d5db-8cc1-4cb9-a499-90602105b49b", "num_reviews": "14", "awards": [], "percent_recommended": null, "distance": ".13", "name": "Stan's Main Street Grill", "see_all_photos": "https://www.tripadvisor.com/Restaurant_Review-g55870-d8523002-m11068-Reviews-Stan_s_Main_Street_Grill-Frisco_Texas.html#photos", "hours": null, "address_obj": {"city": "Frisco", "street1": "7210 Main St", "street2": null, "address_string": "7210 Main St, Frisco, TX 75033-5359", "state": "Texas", "country": "United States", "postalcode": "75033-5359"}, "longitude": "-96.821396"}, {"rating": "3.5", "subcategory": [{"localized_name": "Sit down", "name": "sit_down"}], "bearing": "east", "rating_image_url": "http://www.tripadvisor.com/img/cdsi/img2/ratings/traveler/3.5-11068-5.png", "web_url": "https://www.tripadvisor.com/Restaurant_Review-g55870-d820848-Reviews-m11068-Manny_s_Tex_Mex_Grill-Frisco_Texas.html", "location_id": "820848", "write_review": "https://www.tripadvisor.com/UserReview-g55870-d820848-m11068-Manny_s_Tex_Mex_Grill-Frisco_Texas.html", "cuisine": [{"localized_name": "Mexican", "name": "mexican"}, {"localized_name": "Southwestern", "name": "southwestern"}], "ancestors": [{"abbrv": null, "location_id": "55870", "name": "Frisco", "level": "City"}, {"abbrv": "TX", "location_id": "28964", "name": "Texas", "level": "State"}, {"abbrv": null, "location_id": "191", "name": "United States", "level": "Country"}], "location_string": "Frisco, Texas", "price_level": "$$ - $$$", "latitude": "33.15007", "category": {"localized_name": "Restaurant", "name": "restaurant"}, "ranking_data": {"ranking_string": "#139 of 398 Places to Eat in Frisco", "ranking": "139", "geo_location_name": "Frisco", "geo_location_id": "55870", "ranking_out_of": "398"}, "api_detail_url": "http://api.tripadvisor.com/api/partner/2.0/location/820848?key=b245d5db-8cc1-4cb9-a499-90602105b49b", "num_reviews": "40", "awards": [], "percent_recommended": 72, "distance": ".14", "name": "Manny's Tex Mex Grill", "see_all_photos": "https://www.tripadvisor.com/Restaurant_Review-g55870-d820848-m11068-Reviews-Manny_s_Tex_Mex_Grill-Frisco_Texas.html#photos", "hours": {"timezone": "America/Chicago", "week_ranges": [{"day_name": "Sunday", "localized_day_name": "Sunday", "times": []}, {"day_name": "Monday", "localized_day_name": "Monday", "times": [{"close_time": "21:00", "open_time": "10:30"}]}, {"day_name": "Tuesday", "localized_day_name": "Tuesday", "times": [{"close_time": "21:00", "open_time": "10:30"}]}, {"day_name": "Wednesday", "localized_day_name": "Wednesday", "times": [{"close_time": "21:00", "open_time": "10:30"}]}, {"day_name": "Thursday", "localized_day_name": "Thursday", "times": [{"close_time": "21:00", "open_time": "10:30"}]}, {"day_name": "Friday", "localized_day_name": "Friday", "times": [{"close_time": "22:00", "open_time": "10:30"}]}, {"day_name": "Saturday", "localized_day_name": "Saturday", "times": [{"close_time": "22:00", "open_time": "09:30"}]}]}, "address_obj": {"city": "Frisco", "street1": "7210 W Main St", "street2": "", "address_string": "7210 W Main St, Frisco, TX 75034", "state": "Texas", "country": "United States", "postalcode": "75034"}, "longitude": "-96.82138"}, {"rating": "3.5", "subcategory": [{"localized_name": "Sit down", "name": "sit_down"}], "bearing": "southwest", "rating_image_url": "http://www.tripadvisor.com/img/cdsi/img2/ratings/traveler/3.5-11068-5.png", "web_url": "https://www.tripadvisor.com/Restaurant_Review-g55870-d2676229-Reviews-m11068-La_Unica_Taqueria-Frisco_Texas.html", "location_id": "2676229", "write_review": "https://www.tripadvisor.com/UserReview-g55870-d2676229-m11068-La_Unica_Taqueria-Frisco_Texas.html", "cuisine": [{"localized_name": "Mexican", "name": "mexican"}], "ancestors": [{"abbrv": null, "location_id": "55870", "name": "Frisco", "level": "City"}, {"abbrv": "TX", "location_id": "28964", "name": "Texas", "level": "State"}, {"abbrv": null, "location_id": "191", "name": "United States", "level": "Country"}], "location_string": "Frisco, Texas", "price_level": null, "latitude": "33.14892", "category": {"localized_name": "Restaurant", "name": "restaurant"}, "ranking_data": {"ranking_string": "#304 of 398 Places to Eat in Frisco", "ranking": "304", "geo_location_name": "Frisco", "geo_location_id": "55870", "ranking_out_of": "398"}, "api_detail_url": "http://api.tripadvisor.com/api/partner/2.0/location/2676229?key=b245d5db-8cc1-4cb9-a499-90602105b49b", "num_reviews": "3", "awards": [], "percent_recommended": null, "distance": ".15", "name": "La Unica Taqueria", "see_all_photos": "https://www.tripadvisor.com/Restaurant_Review-g55870-d2676229-m11068-Reviews-La_Unica_Taqueria-Frisco_Texas.html#photos", "hours": null, "address_obj": {"city": "Frisco", "street1": "6942 Pecan St", "street2": "", "address_string": "6942 Pecan St, Frisco, TX 75034-4237", "state": "Texas", "country": "United States", "postalcode": "75034-4237"}, "longitude": "-96.82505"}, {"rating": "4.5", "subcategory": [{"localized_name": "Sit down", "name": "sit_down"}], "bearing": "west", "rating_image_url": "http://www.tripadvisor.com/img/cdsi/img2/ratings/traveler/4.5-11068-5.png", "web_url": "https://www.tripadvisor.com/Restaurant_Review-g55870-d1115689-Reviews-m11068-The_Depot_Cafe-Frisco_Texas.html", "location_id": "1115689", "write_review": "https://www.tripadvisor.com/UserReview-g55870-d1115689-m11068-The_Depot_Cafe-Frisco_Texas.html", "cuisine": [{"localized_name": "American", "name": "american"}, {"localized_name": "Cafe", "name": "cafe"}, {"localized_name": "Diner", "name": "diner"}], "ancestors": [{"abbrv": null, "location_id": "55870", "name": "Frisco", "level": "City"}, {"abbrv": "TX", "location_id": "28964", "name": "Texas", "level": "State"}, {"abbrv": null, "location_id": "191", "name": "United States", "level": "Country"}], "location_string": "Frisco, Texas", "price_level": "$", "latitude": "33.150917", "category": {"localized_name": "Restaurant", "name": "restaurant"}, "ranking_data": {"ranking_string": "#27 of 398 Places to Eat in Frisco", "ranking": "27", "geo_location_name": "Frisco", "geo_location_id": "55870", "ranking_out_of": "398"}, "api_detail_url": "http://api.tripadvisor.com/api/partner/2.0/location/1115689?key=b245d5db-8cc1-4cb9-a499-90602105b49b", "num_reviews": "69", "awards": [{"images": {"small": "http://www.tripadvisor.com/img/cdsi/img2/awards/CERTIFICATE_OF_EXCELLENCE_small-11068-5.jpg", "large": "http://www.tripadvisor.com/img/cdsi/img2/awards/CERTIFICATE_OF_EXCELLENCE_2016_en_US_large-11068-5.jpg"}, "display_name": "Certificate of Excellence 2016", "award_type": "Certificate of Excellence", "categories": [], "year": "2016"}], "percent_recommended": 89, "distance": ".20", "name": "The Depot Cafe", "see_all_photos": "https://www.tripadvisor.com/Restaurant_Review-g55870-d1115689-m11068-Reviews-The_Depot_Cafe-Frisco_Texas.html#photos", "hours": {"timezone": "America/Chicago", "week_ranges": [{"day_name": "Sunday", "localized_day_name": "Sunday", "times": []}, {"day_name": "Monday", "localized_day_name": "Monday", "times": []}, {"day_name": "Tuesday", "localized_day_name": "Tuesday", "times": []}, {"day_name": "Wednesday", "localized_day_name": "Wednesday", "times": []}, {"day_name": "Thursday", "localized_day_name": "Thursday", "times": []}, {"day_name": "Friday", "localized_day_name": "Friday", "times": [{"close_time": "20:30", "open_time": "17:00"}]}, {"day_name": "Saturday", "localized_day_name": "Saturday", "times": []}]}, "address_obj": {"city": "Frisco", "street1": "6733 Main St", "street2": "Main & 3rd Street", "address_string": "6733 Main St Main & 3rd Street, Frisco, TX 75034", "state": "Texas", "country": "United States", "postalcode": "75034"}, "longitude": "-96.82699"}]}