{"paging": {"total_results": "1", "skipped": "0", "previous": null, "results": "1", "next": null}, "data": [{"lang": "en", "rating": 5, "travel_date": null, "title": "Great ice cream treats!Good food!", "url": "https://www.tripadvisor.com/ShowUserReviews-g32872-d4650464-r203638373-m11068-Tastee-Perris_California.html#review203638373", "text": "My family loves the chili burgers,the hamburgers,chili fries too!But by far the best treat is the banana split and dipped cones. Stop in anytime and sit outside enjoying the breeze while eating! Fast friendly service and cheap good food .", "helpful_votes": "0", "rating_image_url": "http://www.tripadvisor.com/img/cdsi/img2/ratings/traveler/s5.0-11068-5.png", "subratings": [], "owner_response": null, "trip_type": "Family", "published_date": "2014-05-01T13:01:43-0400", "location_id": "4650464", "id": "203638373", "user": {"username": "Lisa D", "user_location": {"name": null, "id": null}}}]}