{"paging": {"total_results": "6", "skipped": "0", "previous": null, "results": "6", "next": null}, "data": [{"lang": "en", "rating": 5, "travel_date": "2016-04", "title": "Great Subs", "url": "https://www.tripadvisor.com/ShowUserReviews-g42747-d3716785-r369014021-m11068-Subway-Taylor_Michigan.html#review369014021", "text": "The service is very good and fast.  Always have the bread choice available and fresh. Ordering a foot long they will wrap each half seperate for you.", "helpful_votes": "0", "rating_image_url": "http://www.tripadvisor.com/img/cdsi/img2/ratings/traveler/s5.0-11068-5.png", "subratings": [], "owner_response": null, "trip_type": "Friends getaway", "published_date": "2016-04-30T09:47:28-0400", "location_id": "3716785", "id": "369014021", "user": {"username": "Mary Kathleen C", "user_location": {"name": "Taylor", "id": null}}}, {"lang": "en", "rating": 2, "travel_date": "2015-09", "title": "Descent", "url": "https://www.tripadvisor.com/ShowUserReviews-g42747-d3716785-r345925871-m11068-Subway-Taylor_Michigan.html#review345925871", "text": "I go to subway once a week this location is ok how they make subs, they dont  put many vegetables on even when asked to", "helpful_votes": "0", "rating_image_url": "http://www.tripadvisor.com/img/cdsi/img2/ratings/traveler/s2.0-11068-5.png", "subratings": [{"localized_name": "Service", "name": "rate_service", "value": "3", "rating_image_url": "https://static.tacdn.com/img2/ratings/traveler/ss3.0.gif"}, {"localized_name": "Value", "name": "rate_value", "value": "3", "rating_image_url": "https://static.tacdn.com/img2/ratings/traveler/ss3.0.gif"}, {"localized_name": "Food", "name": "rate_food", "value": "3", "rating_image_url": "https://static.tacdn.com/img2/ratings/traveler/ss3.0.gif"}], "owner_response": null, "trip_type": "Solo travel", "published_date": "2016-02-08T11:55:52-0500", "location_id": "3716785", "id": "345925871", "user": {"username": "E9733QHjamesl", "user_location": {"name": "Taylor, Michigan", "id": "42747"}}}, {"lang": "en", "rating": 5, "travel_date": "2015-10", "title": "Good location.", "url": "https://www.tripadvisor.com/ShowUserReviews-g42747-d3716785-r322680383-m11068-Subway-Taylor_Michigan.html#review322680383", "text": "Many different types of sandwiches to choose from,  They have chips, soup, and coolies.  They have low calorie and meal deals.\n", "helpful_votes": "0", "rating_image_url": "http://www.tripadvisor.com/img/cdsi/img2/ratings/traveler/s5.0-11068-5.png", "subratings": [], "owner_response": null, "trip_type": null, "published_date": "2015-10-28T09:43:12-0400", "location_id": "3716785", "id": "322680383", "user": {"username": "1163Teri", "user_location": {"name": "Taylor, Michigan", "id": "42747"}}}, {"lang": "en", "rating": 5, "travel_date": "2015-07", "title": "Great Subs", "url": "https://www.tripadvisor.com/ShowUserReviews-g42747-d3716785-r298832137-m11068-Subway-Taylor_Michigan.html#review298832137", "text": "This is a great place with great subs.  I have had sandwiches from the lunch and breakfast menu's.  I have eaten inside and have done carry out and drive thru.", "helpful_votes": "0", "rating_image_url": "http://www.tripadvisor.com/img/cdsi/img2/ratings/traveler/s5.0-11068-5.png", "subratings": [], "owner_response": null, "trip_type": null, "published_date": "2015-08-13T08:00:01-0400", "location_id": "3716785", "id": "298832137", "user": {"username": "Angela M", "user_location": {"name": "Taylor", "id": null}}}, {"lang": "en", "rating": 1, "travel_date": "2015-08", "title": "Food poisoning!", "url": "https://www.tripadvisor.com/ShowUserReviews-g42747-d3716785-r296777247-m11068-Subway-Taylor_Michigan.html#review296777247", "text": "Food poisoning from the tuna! Have tried eating here a few times and meat always tastes funny and I won't be going back!", "helpful_votes": "0", "rating_image_url": "http://www.tripadvisor.com/img/cdsi/img2/ratings/traveler/s1.0-11068-5.png", "subratings": [], "owner_response": null, "trip_type": "Solo travel", "published_date": "2015-08-07T21:11:05-0400", "location_id": "3716785", "id": "296777247", "user": {"username": "cgam14", "user_location": {"name": "Taylor, Michigan", "id": "42747"}}}, {"lang": "en", "rating": 3, "travel_date": "2014-04", "title": "Subway is what Subway is; difficult in and out at this location", "url": "https://www.tripadvisor.com/ShowUserReviews-g42747-d3716785-r205525713-m11068-Subway-Taylor_Michigan.html#review205525713", "text": "All Subway locations are pretty much the same so if you like Subway then you are not likely to dislike this location.  My issue with this location is that it can be difficult to enter and exit from this location due to traffic on Telegraph.", "helpful_votes": "1", "rating_image_url": "http://www.tripadvisor.com/img/cdsi/img2/ratings/traveler/s3.0-11068-5.png", "subratings": [{"localized_name": "Service", "name": "rate_service", "value": "3", "rating_image_url": "https://static.tacdn.com/img2/ratings/traveler/ss3.0.gif"}, {"localized_name": "Value", "name": "rate_value", "value": "3", "rating_image_url": "https://static.tacdn.com/img2/ratings/traveler/ss3.0.gif"}, {"localized_name": "Food", "name": "rate_food", "value": "3", "rating_image_url": "https://static.tacdn.com/img2/ratings/traveler/ss3.0.gif"}, {"localized_name": "Atmosphere", "name": "rate_atmosphere", "value": "3", "rating_image_url": "https://static.tacdn.com/img2/ratings/traveler/ss3.0.gif"}], "owner_response": null, "trip_type": "Solo travel", "published_date": "2014-05-14T06:28:27-0400", "location_id": "3716785", "id": "205525713", "user": {"username": "DearbornNative", "user_location": {"name": "Dearborn, Michigan", "id": "42130"}}}]}